{
  "id": "table",
  "type": "SharedSlice",
  "name": "Table",
  "description": "Table",
  "variations": [
    {
      "id": "default",
      "name": "Default",
      "docURL": "...",
      "version": "initial",
      "description": "Default",
      "imageUrl": "",
      "primary": {
        "title": {
          "type": "Text",
          "config": {
            "label": "Title",
            "placeholder": "Optional table caption"
          }
        },
        "table_data": {
          "type": "Table",
          "config": {
            "label": "Table Data"
          }
        },
        "source": {
          "type": "Link",
          "config": {
            "label": "source",
            "placeholder": "",
            "select": null,
            "allowTargetBlank": true,
            "allowText": true,
            "repeat": false
          }
        }
      },
      "items": {}
    }
  ]
}